teedoc_plugin_thumbs_up/__init__.py
teedoc_plugin_thumbs_up/assets/main.js
teedoc_plugin_thumbs_up/assets/style.css
teedoc_plugin_thumbs_up/assets/up.svg
teedoc_plugin_thumbs_up/assets/upped.svg
teedoc_plugin_thumbs_up-1.0.2.dist-info/LICENSE
teedoc_plugin_thumbs_up-1.0.2.dist-info/METADATA
teedoc_plugin_thumbs_up-1.0.2.dist-info/WHEEL
teedoc_plugin_thumbs_up-1.0.2.dist-info/entry_points.txt
teedoc_plugin_thumbs_up-1.0.2.dist-info/top_level.txt
teedoc_plugin_thumbs_up-1.0.2.dist-info/RECORD
