Metadata-Version: 2.1
Name: teedoc-plugin-thumbs-up
Version: 1.0.2
Summary: Thumbs up plugin for teedoc
Home-page: https://github.com/Neutree/teedoc
Author: Neucrack
Author-email: CZD666666@gmail.com
License: MIT
Keywords: advertisement hint teedoc plugin
Platform: UNKNOWN
Classifier: Intended Audience :: Developers
Classifier: License :: OSI Approved :: MIT License
Classifier: Programming Language :: Python :: 3
